odoo/addons/sale_financial_risk_confirm_action/README.rst
odoo/addons/sale_financial_risk_confirm_action/__init__.py
odoo/addons/sale_financial_risk_confirm_action/__manifest__.py
odoo/addons/sale_financial_risk_confirm_action/data/ir_actions_server.xml
odoo/addons/sale_financial_risk_confirm_action/i18n/es.po
odoo/addons/sale_financial_risk_confirm_action/i18n/sale_financial_risk_confirm_action.pot
odoo/addons/sale_financial_risk_confirm_action/readme/CONFIGURE.rst
odoo/addons/sale_financial_risk_confirm_action/readme/CONTRIBUTORS.rst
odoo/addons/sale_financial_risk_confirm_action/readme/DESCRIPTION.rst
odoo/addons/sale_financial_risk_confirm_action/static/description/icon.png
odoo/addons/sale_financial_risk_confirm_action/static/description/index.html
odoo/addons/sale_financial_risk_confirm_action/wizards/__init__.py
odoo/addons/sale_financial_risk_confirm_action/wizards/parner_risk_exceeded.py
odoo/addons/sale_financial_risk_confirm_action/wizards/partner_risk_exceeded_view.xml
odoo_addon_sale_financial_risk_confirm_action-15.0.1.0.0.1.dist-info/METADATA
odoo_addon_sale_financial_risk_confirm_action-15.0.1.0.0.1.dist-info/WHEEL
odoo_addon_sale_financial_risk_confirm_action-15.0.1.0.0.1.dist-info/top_level.txt
odoo_addon_sale_financial_risk_confirm_action-15.0.1.0.0.1.dist-info/RECORD
