Metadata-Version: 2.1
Name: odoo-addon-sale_financial_risk_confirm_action
Version: 15.0.1.0.0.1
Summary: Allow confirm sale order in risk exception but changing several sale order fields
Home-page: https://github.com/OCA/credit-control
Author: Tecnativa, Odoo Community Association (OCA)
Author-email: support@odoo-community.org
License: AGPL-3
Classifier: Programming Language :: Python
Classifier: Framework :: Odoo
Classifier: Framework :: Odoo :: 15.0
Classifier: License :: OSI Approved :: GNU Affero General Public License v3
Classifier: Development Status :: 4 - Beta
Requires-Python: >=3.8
Requires-Dist: odoo-addon-sale-financial-risk<15.1dev,>=15.0dev
Requires-Dist: odoo<15.1dev,>=15.0a
